SCons/Action.py
SCons/Builder.py
SCons/CacheDir.py
SCons/Conftest.py
SCons/Debug.py
SCons/Defaults.py
SCons/Environment.py
SCons/Errors.py
SCons/Executor.py
SCons/Job.py
SCons/Memoize.py
SCons/PathList.py
SCons/SConf.py
SCons/SConsign.py
SCons/Sig.py
SCons/Subst.py
SCons/Taskmaster.py
SCons/Util.py
SCons/Warnings.py
SCons/__init__.py
SCons/cpp.py
SCons/dblite.py
SCons/exitfuncs.py
SCons/Node/Alias.py
SCons/Node/FS.py
SCons/Node/Python.py
SCons/Node/__init__.py
SCons/Options/BoolOption.py
SCons/Options/EnumOption.py
SCons/Options/ListOption.py
SCons/Options/PackageOption.py
SCons/Options/PathOption.py
SCons/Options/__init__.py
SCons/Platform/__init__.py
SCons/Platform/aix.py
SCons/Platform/cygwin.py
SCons/Platform/darwin.py
SCons/Platform/hpux.py
SCons/Platform/irix.py
SCons/Platform/os2.py
SCons/Platform/posix.py
SCons/Platform/sunos.py
SCons/Platform/win32.py
SCons/Scanner/C.py
SCons/Scanner/D.py
SCons/Scanner/Dir.py
SCons/Scanner/Fortran.py
SCons/Scanner/IDL.py
SCons/Scanner/LaTeX.py
SCons/Scanner/Prog.py
SCons/Scanner/RC.py
SCons/Scanner/__init__.py
SCons/Script/Interactive.py
SCons/Script/Main.py
SCons/Script/SConsOptions.py
SCons/Script/SConscript.py
SCons/Script/__init__.py
SCons/Tool/386asm.py
SCons/Tool/BitKeeper.py
SCons/Tool/CVS.py
SCons/Tool/FortranCommon.py
SCons/Tool/GettextCommon.py
SCons/Tool/JavaCommon.py
SCons/Tool/Perforce.py
SCons/Tool/PharLapCommon.py
SCons/Tool/RCS.py
SCons/Tool/SCCS.py
SCons/Tool/Subversion.py
SCons/Tool/__init__.py
SCons/Tool/aixc++.py
SCons/Tool/aixcc.py
SCons/Tool/aixf77.py
SCons/Tool/aixlink.py
SCons/Tool/applelink.py
SCons/Tool/ar.py
SCons/Tool/as.py
SCons/Tool/bcc32.py
SCons/Tool/c++.py
SCons/Tool/cc.py
SCons/Tool/cvf.py
SCons/Tool/cyglink.py
SCons/Tool/default.py
SCons/Tool/dmd.py
SCons/Tool/dvi.py
SCons/Tool/dvipdf.py
SCons/Tool/dvips.py
SCons/Tool/f03.py
SCons/Tool/f77.py
SCons/Tool/f90.py
SCons/Tool/f95.py
pystick-0.1.6.dist-info/DESCRIPTION.rst
pystick-0.1.6.dist-info/METADATA
pystick-0.1.6.dist-info/RECORD
pystick-0.1.6.dist-info/WHEEL
pystick-0.1.6.dist-info/entry_points.txt
pystick-0.1.6.dist-info/metadata.json
pystick-0.1.6.dist-info/namespace_packages.txt
pystick-0.1.6.dist-info/top_level.txt
